rythmnet_functions/__init__.py
rythmnet_functions/utils_func/__init__.py
rythmnet_functions/utils_func/engine_vipl.py
rythmnet_functions/utils_func/model_utils.py
rythmnet_functions/utils_func/plot_scripts.py
rythmnet_functions/utils_func/resnet.py
rythmnet_functions/utils_func/rhythmnet.py
rythmnet_functions/utils_func/rhythmnet_loss.py
rythmnet_functions-0.0.1.dist-info/METADATA
rythmnet_functions-0.0.1.dist-info/WHEEL
rythmnet_functions-0.0.1.dist-info/top_level.txt
rythmnet_functions-0.0.1.dist-info/RECORD
